llmsearch/__init__.py
llmsearch/_version.py
llmsearch/api.py
llmsearch/chroma.py
llmsearch/cli.py
llmsearch/config.py
llmsearch/embeddings.py
llmsearch/interact.py
llmsearch/process.py
llmsearch/ranking.py
llmsearch/splade.py
llmsearch/utils.py
llmsearch/webapp.py
llmsearch/database/__init__.py
llmsearch/database/config.py
llmsearch/database/crud.py
llmsearch/database/models.py
llmsearch/models/__init__.py
llmsearch/models/abstract.py
llmsearch/models/autogptq.py
llmsearch/models/azureopenai.py
llmsearch/models/config.py
llmsearch/models/hf.py
llmsearch/models/llama.py
llmsearch/models/openai.py
llmsearch/models/utils.py
llmsearch/obsolete/cli.bck
llmsearch/obsolete/main.py
llmsearch/obsolete/prompts.py
llmsearch/parsers/__init__.py
llmsearch/parsers/doc.py
llmsearch/parsers/experimental.py
llmsearch/parsers/markdown.py
llmsearch/parsers/pdf.py
llmsearch/parsers/splitter.py
llmsearch/parsers/unstructured.py
llmsearch/parsers/images/__init__.py
llmsearch/parsers/images/gemini_parser.py
llmsearch/parsers/images/generic.py
llmsearch/parsers/tables/__ini__.py
llmsearch/parsers/tables/azuredocint_parser.py
llmsearch/parsers/tables/generic.py
llmsearch/parsers/tables/gmft_parser.py
pyllmsearch-0.9.5.dist-info/licenses/LICENSE
pyllmsearch-0.9.5.dist-info/METADATA
pyllmsearch-0.9.5.dist-info/WHEEL
pyllmsearch-0.9.5.dist-info/entry_points.txt
pyllmsearch-0.9.5.dist-info/top_level.txt
pyllmsearch-0.9.5.dist-info/RECORD
