Metadata-Version: 2.4
Name: pyllmsearch
Version: 0.9.5
Summary: LLM Powered Advanced RAG Application
Project-URL: Homepage, https://github.com/snexus/llm-search
Project-URL: Documentation, https://llm-search.readthedocs.io/en/latest/
Keywords: llm,rag,retrieval-augemented-generation,large-language-models,local,splade,hyde,reranking,chroma,openai
Classifier: License :: OSI Approved :: MIT License
Classifier: Operating System :: OS Independent
Classifier: Programming Language :: Python :: 3 :: Only
Classifier: Programming Language :: Python :: 3.10
Classifier: Programming Language :: Python :: 3.11
Requires-Python: >=3.10
License-File: LICENSE
Requires-Dist: langchain-community>=0.4.1
Requires-Dist: langchain>=1.2.4
Requires-Dist: langchain-huggingface>=1.2.0
Requires-Dist: langchain-chroma>=1.1.0
Requires-Dist: python-dotenv>=1.2.1
Requires-Dist: loguru>=0.7.3
Requires-Dist: click>=8.3.1
Requires-Dist: openai>=2.15.0
Requires-Dist: streamlit>=1.53.0
Requires-Dist: tenacity>=9.1.2
Requires-Dist: tqdm>=4.67.1
Requires-Dist: gmft==0.2.1
Requires-Dist: pypdf2>=3.0.1
Requires-Dist: pydantic>=2.12.5
Requires-Dist: instructorembedding>=1.0.1
Requires-Dist: unstructured>=0.18.27
Requires-Dist: tiktoken>=0.12.0
Requires-Dist: tokenizers>=0.22.2
Requires-Dist: langchain-openai>=1.1.7
Requires-Dist: python-docx>=1.2.0
Requires-Dist: pymupdf>=1.26.7
Requires-Dist: termcolor>=3.3.0
Requires-Dist: fastapi-mcp>=0.4.0
Requires-Dist: scipy>=1.15.3
Requires-Dist: sentence-transformers>=5.2.0
Provides-Extra: dev
Requires-Dist: black; extra == "dev"
Requires-Dist: pytest; extra == "dev"
Requires-Dist: pytest-cov; extra == "dev"
Requires-Dist: ruff; extra == "dev"
Requires-Dist: autodoc_pydantic; extra == "dev"
Requires-Dist: sphinx; extra == "dev"
Requires-Dist: sphinx-markdown-builder; extra == "dev"
Requires-Dist: sphinx_rtd_theme; extra == "dev"
Provides-Extra: azureparser
Requires-Dist: azure-ai-documentintelligence==1.0.0b3; extra == "azureparser"
Requires-Dist: azure-identity==1.17.1; extra == "azureparser"
Provides-Extra: googleparser
Requires-Dist: google-generativeai>=0.8.5; extra == "googleparser"
Dynamic: license-file
